odoo/addons/ssi_helpdesk/README.rst
odoo/addons/ssi_helpdesk/__init__.py
odoo/addons/ssi_helpdesk/__manifest__.py
odoo/addons/ssi_helpdesk/menu.xml
odoo/addons/ssi_helpdesk/data/approval_template_data.xml
odoo/addons/ssi_helpdesk/data/base_automation_data.xml
odoo/addons/ssi_helpdesk/data/ir_actions_server_data.xml
odoo/addons/ssi_helpdesk/data/ir_sequence_data.xml
odoo/addons/ssi_helpdesk/data/policy_template_data.xml
odoo/addons/ssi_helpdesk/data/sequence_template_data.xml
odoo/addons/ssi_helpdesk/i18n/ssi_helpdesk.pot
odoo/addons/ssi_helpdesk/models/__init__.py
odoo/addons/ssi_helpdesk/models/helpdesk_channel.py
odoo/addons/ssi_helpdesk/models/helpdesk_communication.py
odoo/addons/ssi_helpdesk/models/helpdesk_contact_group.py
odoo/addons/ssi_helpdesk/models/helpdesk_data_requirement_type.py
odoo/addons/ssi_helpdesk/models/helpdesk_resolution_documentation_type.py
odoo/addons/ssi_helpdesk/models/helpdesk_ticket.py
odoo/addons/ssi_helpdesk/models/helpdesk_ticket_data_requirement.py
odoo/addons/ssi_helpdesk/models/helpdesk_ticket_resolution_documentation.py
odoo/addons/ssi_helpdesk/models/helpdesk_type.py
odoo/addons/ssi_helpdesk/models/helpdesk_type_category.py
odoo/addons/ssi_helpdesk/security/ir.model.access.csv
odoo/addons/ssi_helpdesk/security/ir_module_category_data.xml
odoo/addons/ssi_helpdesk/security/res_group_data.xml
odoo/addons/ssi_helpdesk/static/description/icon.png
odoo/addons/ssi_helpdesk/views/helpdesk_channel_views.xml
odoo/addons/ssi_helpdesk/views/helpdesk_communication_views.xml
odoo/addons/ssi_helpdesk/views/helpdesk_contact_group_views.xml
odoo/addons/ssi_helpdesk/views/helpdesk_data_requirement_type_views.xml
odoo/addons/ssi_helpdesk/views/helpdesk_resolution_documentation_type_views.xml
odoo/addons/ssi_helpdesk/views/helpdesk_ticket_views.xml
odoo/addons/ssi_helpdesk/views/helpdesk_type_category_views.xml
odoo/addons/ssi_helpdesk/views/helpdesk_type_views.xml
odoo/addons/ssi_helpdesk/wizards/__init__.py
odoo14_addon_ssi_helpdesk-14.0.3.2.1.dist-info/METADATA
odoo14_addon_ssi_helpdesk-14.0.3.2.1.dist-info/WHEEL
odoo14_addon_ssi_helpdesk-14.0.3.2.1.dist-info/top_level.txt
odoo14_addon_ssi_helpdesk-14.0.3.2.1.dist-info/RECORD
